autogen_openaiext_client/__init__.py
autogen_openaiext_client/client.py
autogen_openaiext_client/info.py
autogen_openaiext_client-0.0.3.dist-info/LICENSE
autogen_openaiext_client-0.0.3.dist-info/METADATA
autogen_openaiext_client-0.0.3.dist-info/WHEEL
autogen_openaiext_client-0.0.3.dist-info/top_level.txt
autogen_openaiext_client-0.0.3.dist-info/RECORD
