Metadata-Version: 2.2
Name: autogen_openaiext_client
Version: 0.0.3
Summary: This is an autogen>=0.4 extension for integrating external models through the OpenAI API.
Author-email: Vaibhav Balloli <balloli.vb@gmail.com>
License: MIT License
Keywords: autogen,agent
Classifier: Programming Language :: Python :: 3
Requires-Python: <3.13,>=3.10
License-File: LICENSE
Requires-Dist: autogen-core>=0.4.0
